bayesian_dpddm/__init__.py
bayesian_dpddm/_metadata.py
bayesian_dpddm/configs/__init__.py
bayesian_dpddm/configs/model_configs.py
bayesian_dpddm/configs/train_configs.py
bayesian_dpddm/models/__init__.py
bayesian_dpddm/models/base.py
bayesian_dpddm/models/conv_model.py
bayesian_dpddm/models/mlp_model.py
bayesian_dpddm/models/resnet_model.py
bayesian_dpddm/models/utils.py
bayesian_dpddm/monitors/__init__.py
bayesian_dpddm/monitors/bayesian_monitor.py
bayesian_dpddm/monitors/full_information_monitor.py
bayesian_dpddm/monitors/monitor.py
bayesian_dpddm/monitors/utils.py
bayesian_dpddm-1.0.6.dist-info/licenses/LICENSE
bayesian_dpddm-1.0.6.dist-info/METADATA
bayesian_dpddm-1.0.6.dist-info/WHEEL
bayesian_dpddm-1.0.6.dist-info/top_level.txt
bayesian_dpddm-1.0.6.dist-info/RECORD
