Metadata-Version: 2.4
Name: bayesian_dpddm
Version: 1.0.6
Summary: Implements Bayesian D-PDDM for Post-Deployment Deterioration Monitoring of ML models.
Author-email: viet <viet@cs.toronto.edu>, sid <sid.arya@mail.utoronto.ca>
License: MIT License
Project-URL: homepage, https://github.com/teivng/bayesian_dpddm
Classifier: Programming Language :: Python :: 3.11
Classifier: License :: OSI Approved :: MIT License
Classifier: Operating System :: OS Independent
Requires-Python: >=3.11
License-File: LICENSE
Requires-Dist: numpy>=1.26.4
Requires-Dist: torch>=2.5.1
Requires-Dist: torchvision>=0.20.1
Requires-Dist: vbll>=0.2.6
Requires-Dist: tqdm>=4.66.5
Requires-Dist: matplotlib>=3.10.0
Requires-Dist: pillow>=11.0.0
Requires-Dist: wandb>=0.19.6
Requires-Dist: hydra-core>=1.3.2
Requires-Dist: wilds>=2.0.0
Requires-Dist: twine
Requires-Dist: build
Dynamic: license-file
